binette/__init__.py
binette/bin_manager.py
binette/bin_quality.py
binette/cds.py
binette/contig_manager.py
binette/diamond.py
binette/io_manager.py
binette/main.py
binette-1.2.1.dist-info/licenses/LICENSE
binette-1.2.1.dist-info/METADATA
binette-1.2.1.dist-info/WHEEL
binette-1.2.1.dist-info/entry_points.txt
binette-1.2.1.dist-info/top_level.txt
binette-1.2.1.dist-info/RECORD
