Metadata-Version: 2.4
Name: Binette
Version: 1.2.1
Summary: Binette: accurate binning refinement tool to constructs high quality MAGs.
Author: Jean Mainguy
Maintainer: Jean Mainguy
Project-URL: Repository, https://github.com/genotoul-bioinfo/Binette
Project-URL: Documentation, https://binette.readthedocs.io
Keywords: Bioinformatics,Prokaryote,Binning,Refinement,Metagenomics
Classifier: Environment :: Console
Classifier: Intended Audience :: Science/Research
Classifier: Natural Language :: English
Classifier: Operating System :: POSIX :: Linux
Classifier: Programming Language :: Python :: 3
Classifier: Topic :: Scientific/Engineering :: Bio-Informatics
Requires-Python: >=3.12
License-File: LICENSE
Requires-Dist: joblib<2.0,>=1.0
Requires-Dist: networkx<4.0,>=3.0
Requires-Dist: numpy<3.0,>1.24
Requires-Dist: pandas<3,>=2
Requires-Dist: pyfastx<3,>=2
Requires-Dist: pyrodigal<4,>=3
Requires-Dist: pyroaring<2.0.0,>=1.0.0
Requires-Dist: typer<1.0.0,>=0.9.0
Requires-Dist: rich<14.0.0,>=12.0.0
Provides-Extra: doc
Requires-Dist: sphinx==6.2.1; extra == "doc"
Requires-Dist: sphinx_rtd_theme==1.2.2; extra == "doc"
Requires-Dist: readthedocs-sphinx-search==0.3.1; extra == "doc"
Requires-Dist: sphinx-autobuild==2021.3.14; extra == "doc"
Requires-Dist: myst-parser==1.0.0; extra == "doc"
Requires-Dist: docutils==0.18.1; extra == "doc"
Requires-Dist: nbsphinx==0.9.5; extra == "doc"
Requires-Dist: nbsphinx_link==1.3.0; extra == "doc"
Requires-Dist: sphinx-book-theme==1.0.1; extra == "doc"
Requires-Dist: sphinxcontrib.mermaid; extra == "doc"
Requires-Dist: sphinx_togglebutton==0.3.2; extra == "doc"
Provides-Extra: dev
Requires-Dist: pytest>=7.0.0; extra == "dev"
Requires-Dist: pytest-cov; extra == "dev"
Requires-Dist: ruff>=0.1.0; extra == "dev"
Dynamic: license-file
